README.md
setup.py
tiling3d/__init__.py
tiling3d/tiles.py
tiling3d/tiling_objects.py
tiling3d/tiling_solver.py
tiling3d/visualization.py
tiling3d.egg-info/PKG-INFO
tiling3d.egg-info/SOURCES.txt
tiling3d.egg-info/dependency_links.txt
tiling3d.egg-info/requires.txt
tiling3d.egg-info/top_level.txt