Metadata-Version: 2.1
Name: tiling3d
Version: 0.0.7
Summary: Tiling solver
Home-page: https://github.com/Thilo-J/Tiling3D
Author: Thilo Langensteiner
Author-email: <thilo.j.la@gmail.com>
License: UNKNOWN
Project-URL: GitHub, https://github.com/Thilo-J/Tiling3D
Keywords: python,ubongo,tiling,3d,polyomino
Platform: UNKNOWN
Classifier: Development Status :: 4 - Beta
Classifier: Intended Audience :: Education
Classifier: Programming Language :: Python :: 3
Classifier: Operating System :: Unix
Classifier: Operating System :: MacOS :: MacOS X
Classifier: Operating System :: Microsoft :: Windows
